lotuschat_sdk/__init__.py
lotuschat_sdk/control/__init__.py
lotuschat_sdk/control/api_command.py
lotuschat_sdk/control/api_group.py
lotuschat_sdk/control/api_message.py
lotuschat_sdk/control/bot.py
lotuschat_sdk/control/const.py
lotuschat_sdk/model/__init__.py
lotuschat_sdk/model/media.py
lotuschat_sdk/model/message.py
lotuschat_sdk/model/notify.py
lotuschat_sdk/model/query.py
lotuschat_sdk/model/request.py
lotuschat_sdk/utility/__init__.py
lotuschat_sdk/utility/logger.py
lotuschat_sdk/utility/utility.py
lotuschat_bot_sdk-0.2.3.dist-info/METADATA
lotuschat_bot_sdk-0.2.3.dist-info/WHEEL
lotuschat_bot_sdk-0.2.3.dist-info/top_level.txt
lotuschat_bot_sdk-0.2.3.dist-info/RECORD
