Metadata-Version: 2.4
Name: lotuschat_bot_sdk
Version: 0.2.3
Summary: SDK for interacting with LotusChat API
Author-email: Yuriko <tunguyenanh@vccorp.vn>
License: MIT
Requires-Dist: requests==2.32.4
Requires-Dist: schedule==1.2.2
Requires-Dist: flask==3.1.1
Requires-Dist: pydantic==2.11.7
Requires-Dist: aiohttp==3.12.14
Requires-Dist: quart==0.20.0
Requires-Dist: asgiref==3.9.1
